README.md
setup.py
tsl294/__init__.py
tsl294/client.py
tsl294/packet.py
tsl294.egg-info/PKG-INFO
tsl294.egg-info/SOURCES.txt
tsl294.egg-info/dependency_links.txt
tsl294.egg-info/requires.txt
tsl294.egg-info/top_level.txt
tsl294/crypto/__init__.py
tsl294/crypto/hash.py
tsl294/crypto/key.py