Metadata-Version: 2.1
Name: tsl294
Version: 0.9.1
Summary: Transport secure layer version 294
Home-page: https://github.com/draklowell/TSL294
Author: Drak Lowell
License: Apache License 2.0
Platform: UNKNOWN
Classifier: Programming Language :: Python :: 3
Classifier: License :: OSI Approved :: MIT License
Classifier: Operating System :: OS Independent
Classifier: Development Status :: 4 - Beta
Classifier: Natural Language :: English
Requires-Python: >=3.8
